stabilizer_toolkit/__init__.py
stabilizer_toolkit/decompositions/__init__.py
stabilizer_toolkit/decompositions/rank2/__init__.py
stabilizer_toolkit/decompositions/rank2/search_all_stabilizer_states.py
stabilizer_toolkit/decompositions/rank2/ternary_search.py
stabilizer_toolkit/decompositions/validate.py
stabilizer_toolkit/helpers/__init__.py
stabilizer_toolkit/helpers/ray.py
stabilizer_toolkit/helpers/unitary.py
stabilizer_toolkit/helpers/vector.py
stabilizer_toolkit/magic_states/__init__.py
stabilizer_toolkit/magic_states/ccz.py
stabilizer_toolkit/magic_states/t.py
stabilizer_toolkit-0.1.0.dist-info/LICENSE
stabilizer_toolkit-0.1.0.dist-info/METADATA
stabilizer_toolkit-0.1.0.dist-info/WHEEL
stabilizer_toolkit-0.1.0.dist-info/RECORD
