Metadata-Version: 2.1
Name: stabilizer-toolkit
Version: 0.1.0
Summary: A toolkit for working with the stabilizer formalism: stabilizer states, rank, decompositions, etc.
License: Apache-2.0
Author: Amir Ebrahimi
Author-email: github@aebrahimi.com
Requires-Python: >=3.9,<4.0
Classifier: License :: OSI Approved :: Apache Software License
Classifier: Programming Language :: Python :: 3
Classifier: Programming Language :: Python :: 3.9
Classifier: Programming Language :: Python :: 3.10
Classifier: Programming Language :: Python :: 3.11
Provides-Extra: helpers
Provides-Extra: states
Requires-Dist: cirq (>=1.1.0,<2.0.0) ; extra == "helpers"
Requires-Dist: numpy (>=1.23,<1.24)
Requires-Dist: psutil (>=5.9.5,<6.0.0)
Requires-Dist: ray (>=2.3.1,<3.0.0)
Requires-Dist: stabilizer-states (>=0.1.1,<0.2.0) ; extra == "states"
Requires-Dist: tqdm (>=4.65.0,<5.0.0)
